llm_adaptive_router/__init__.py
llm_adaptive_router/models.py
llm_adaptive_router/prompts.py
llm_adaptive_router/router.py
llm_adaptive_router/utils.py
tests/__init__.py
tests/test_router.py
llm_adaptive_router-0.1.13.dist-info/LICENSE
llm_adaptive_router-0.1.13.dist-info/METADATA
llm_adaptive_router-0.1.13.dist-info/WHEEL
llm_adaptive_router-0.1.13.dist-info/top_level.txt
llm_adaptive_router-0.1.13.dist-info/RECORD
