Metadata-Version: 2.1
Name: llm_adaptive_router
Version: 0.1.13
Summary: An adaptive router for LLM model selection
Home-page: https://github.com/emingenc/llm_adaptive_router
Author: Emin Genc
Author-email: emingench@gmail.com
Project-URL: Homepage, https://github.com/emingenc/llm_adaptive_router
Project-URL: Source, https://github.com/emingenc/llm_adaptive_router
Project-URL: Issue Tracker, https://github.com/emingenc/llm_adaptive_router/issues
Keywords: llm,router,adaptive,llm-adaptive-router,llm-router
Classifier: Development Status :: 4 - Beta
Classifier: Intended Audience :: Developers
Classifier: License :: OSI Approved :: Apache Software License
Classifier: Programming Language :: Python :: 3
Classifier: Operating System :: OS Independent
Classifier: Topic :: Software Development :: Libraries :: Python Modules
Requires-Python: >=3.9
License-File: LICENSE
Requires-Dist: langchain >=0.3.1
Requires-Dist: langchain-community >=0.3.1
Requires-Dist: langchain-core >=0.3.8
Requires-Dist: langchain-openai >=0.2.1
Requires-Dist: langchain-text-splitters >=0.3.0
